mycalc/calculator.py
mycalc_koj-0.0.1.dist-info/LICENSE
mycalc_koj-0.0.1.dist-info/METADATA
mycalc_koj-0.0.1.dist-info/WHEEL
mycalc_koj-0.0.1.dist-info/top_level.txt
mycalc_koj-0.0.1.dist-info/RECORD
